<?xml version="1.0" encoding="UTF-8"?>
<difference>
   <type name="StructureDefinition" status="changed">
      <element binding-status="changed"
               binding-valueset-changed="true"
               path="StructureDefinition.status">
         <old-binding reference="http://hl7.org/fhir/ValueSet/publication-status|4.0.0"
                      strength="required"/>
         <new-binding reference="http://hl7.org/fhir/ValueSet/publication-status|4.1.0"
                      strength="required"/>
      </element>
      <element binding-status="changed"
               binding-valueset-changed="true"
               path="StructureDefinition.fhirVersion">
         <old-binding reference="http://hl7.org/fhir/ValueSet/FHIR-version|4.0.0"
                      strength="required"/>
         <new-binding reference="http://hl7.org/fhir/ValueSet/FHIR-version|4.1.0"
                      strength="required"/>
      </element>
      <element binding-status="changed"
               binding-valueset-changed="true"
               path="StructureDefinition.kind">
         <old-binding reference="http://hl7.org/fhir/ValueSet/structure-definition-kind|4.0.0"
                      strength="required"/>
         <new-binding reference="http://hl7.org/fhir/ValueSet/structure-definition-kind|4.1.0"
                      strength="required"/>
      </element>
      <element binding-status="changed"
               binding-valueset-changed="true"
               path="StructureDefinition.context.type">
         <old-binding reference="http://hl7.org/fhir/ValueSet/extension-context-type|4.0.0"
                      strength="required"/>
         <new-binding reference="http://hl7.org/fhir/ValueSet/extension-context-type|4.1.0"
                      strength="required"/>
      </element>
      <element binding-status="changed"
               binding-valueset-changed="true"
               path="StructureDefinition.derivation">
         <old-binding reference="http://hl7.org/fhir/ValueSet/type-derivation-rule|4.0.0"
                      strength="required"/>
         <new-binding reference="http://hl7.org/fhir/ValueSet/type-derivation-rule|4.1.0"
                      strength="required"/>
      </element>
   </type>
</difference>
